titanfe/__init__.py
titanfe/brick.py
titanfe/config.py
titanfe/connection.py
titanfe/constants.py
titanfe/get-pip.py
titanfe/log.py
titanfe/log_config.yml
titanfe/messages.py
titanfe/repository.py
titanfe/ujo_helper.py
titanfe/utils.py
titanfe/apps/__init__.py
titanfe/apps/brick_runner/__init__.py
titanfe/apps/brick_runner/__main__.py
titanfe/apps/brick_runner/adapter.py
titanfe/apps/brick_runner/brick.py
titanfe/apps/brick_runner/connection.py
titanfe/apps/brick_runner/grid_manager.py
titanfe/apps/brick_runner/input.py
titanfe/apps/brick_runner/metrics.py
titanfe/apps/brick_runner/packet.py
titanfe/apps/brick_runner/runner.py
titanfe/apps/brick_runner/output/__init__.py
titanfe/apps/brick_runner/output/consumer.py
titanfe/apps/brick_runner/output/group.py
titanfe/apps/brick_runner/output/output.py
titanfe/apps/brick_runner/output/port.py
titanfe/apps/control_peer/__init__.py
titanfe/apps/control_peer/__main__.py
titanfe/apps/control_peer/brick.py
titanfe/apps/control_peer/config.yaml
titanfe/apps/control_peer/control_peer.py
titanfe/apps/control_peer/runner.py
titanfe/apps/control_peer/services.py
titanfe/apps/control_peer/webapi/__init__.py
titanfe/apps/control_peer/webapi/app.py
titanfe/apps/control_peer/webapi/bricks.py
titanfe/apps/control_peer/webapi/flows.py
titanfe/apps/control_peer/webapi/state.py
titanfe/apps/kafka_to_elastic/__init__.py
titanfe/apps/kafka_to_elastic/__main__.py
titanfe/apps/kafka_viewer/__init__.py
titanfe/apps/kafka_viewer/__main__.py
titanfe/testing/__init__.py
titanfe/testing/testrunner.py
titanfe-0.4.190.dist-info/METADATA
titanfe-0.4.190.dist-info/RECORD
titanfe-0.4.190.dist-info/WHEEL
titanfe-0.4.190.dist-info/top_level.txt
