Metadata-Version: 2.1
Name: titanfe
Version: 0.4.190
Summary: titan Data Flow Engine for Python
Home-page: http://www.industrial-devops.org/
Author: wobe-systems GmbH
Author-email: info@industrial-devops.org
License: Apache License, Version 2.0
Project-URL: Bug Tracker, https://tracker.industrial-devops.org
Project-URL: Documentation, https://readthedocs.org/projects/titanfe
Project-URL: Source Code, https://git.industrial-devops.org/titan/DataFlowEngine/flowengine-py
Platform: Windows
Platform: Linux
Classifier: Programming Language :: Python :: 3
Classifier: License :: OSI Approved :: Apache Software License
Classifier: Operating System :: Microsoft :: Windows
Classifier: Operating System :: POSIX :: Linux
Classifier: Development Status :: 3 - Alpha
Classifier: Programming Language :: Python :: 3 :: Only
Classifier: Programming Language :: Python :: 3.7
Requires-Dist: ujotypes (>=0.1.2)
Requires-Dist: ujoschema (>=0.3.66)
Requires-Dist: ruamel.yaml
Requires-Dist: janus
Requires-Dist: aiokafka (==0.5.2)
Requires-Dist: kafka-python (==1.4.6)
Requires-Dist: elasticsearch (==7.8.*)
Requires-Dist: fastapi
Requires-Dist: uvicorn (==0.9.*)
Requires-Dist: aiohttp (>=3.6.2)
Requires-Dist: aiohttp-requests (>=0.1.3)
Requires-Dist: dataclasses-json
Requires-Dist: requests
Requires-Dist: docopt
Requires-Dist: pycryptodome
Requires-Dist: uvloop (==0.13.*); platform_system == "Linux"
